hnyconfig/__init__.py
hnyconfig/clas.py
hny_config-0.1.0.dist-info/METADATA
hny_config-0.1.0.dist-info/WHEEL
hny_config-0.1.0.dist-info/top_level.txt
hny_config-0.1.0.dist-info/RECORD
