Metadata-Version: 2.1
Name: hny-config
Version: 0.1.0
Summary: UNKNOWN
Home-page: https://github.com/Soldy/hny-config
Author: Soldy
License: UNKNOWN
Platform: UNKNOWN
Classifier: Development Status :: 2 - Pre-Alpha
Classifier: Programming Language :: Python :: 3
Classifier: Operating System :: OS Independent
Classifier: License :: OSI Approved :: GNU Lesser General Public License v3 (LGPLv3)
Classifier: Topic :: Utilities
Provides-Extra: dev
Requires-Dist: pytest (>=6.2) ; extra == 'dev'
